mlcoder/__init__.py
mlcoder/cli.py
mlcoder/file.py
mlcoder/ui.py
mlcoder/files/pretty_print.py
mlcoder/files/reinforcement/RL_from_real_scratch_concise.ipynb
mlcoder/files/training/Fine_Tuning_with_SFTTrainer.ipynb
mlcoder/files/ui/ui_pretty_print.py
mlcoder-0.1.3.dist-info/LICENSE
mlcoder-0.1.3.dist-info/METADATA
mlcoder-0.1.3.dist-info/WHEEL
mlcoder-0.1.3.dist-info/entry_points.txt
mlcoder-0.1.3.dist-info/top_level.txt
mlcoder-0.1.3.dist-info/RECORD
