Metadata-Version: 2.2
Name: mlcoder
Version: 0.1.3
Summary: MLCoder is a Python package that provides a collection of frequently used code snippets for Machine Learning, offering a command-line interface (CLI) to search and copy files from its built-in repository. Users can easily install it via PyPI or GitHub and leverage its simple commands to quickly access useful scripts.
Home-page: https://github.com/hissain/mlcoder
Author: Md. Sazzad Hissain Khan
Author-email: hissain.khan@gmail.com
Classifier: Programming Language :: Python :: 3
Classifier: License :: OSI Approved :: MIT License
Classifier: Operating System :: OS Independent
Requires-Python: >=3.11
License-File: LICENSE
Requires-Dist: numpy
Dynamic: author
Dynamic: author-email
Dynamic: classifier
Dynamic: description
Dynamic: description-content-type
Dynamic: home-page
Dynamic: requires-dist
Dynamic: requires-python
Dynamic: summary
